rtisdevremotepy/RTISDevRemotePy.py
rtisdevremotepy/RTISDevRemotePy2.py
rtisdevremotepy/UpdateDoc.py
rtisdevremotepy/__init__.py
rtisdevremotepy/rtisdevremote/RTISDevRemote.py
rtisdevremotepy/rtisdevremote/__init__.py
rtisdevremotepy-2.15.1.dist-info/LICENSE
rtisdevremotepy-2.15.1.dist-info/METADATA
rtisdevremotepy-2.15.1.dist-info/WHEEL
rtisdevremotepy-2.15.1.dist-info/top_level.txt
rtisdevremotepy-2.15.1.dist-info/RECORD
