Metadata-Version: 2.1
Name: rtisdevremotepy
Version: 2.15.1
Summary: Python wrapper for using RTIS Dev remotely
Author-email: Wouter Jansen <wouter.jansen@uantwerpen.be>
License: Attribution-NonCommercial-ShareAlike 4.0 International
Project-URL: Repository, https://cosysgit.uantwerpen.be/rtis-software/rtisdevremotepy
Project-URL: Documentation, https://cosysgit.uantwerpen.be/rtis-software/rtisdevremotepy/-/wikis/home
Keywords: rtisdev,rtis,sonar,wrapper
Classifier: Development Status :: 6 - Mature
Classifier: Programming Language :: Python
Classifier: Programming Language :: Python :: 3
Classifier: Programming Language :: Python :: 3.6
Classifier: Programming Language :: Python :: 3.7
Classifier: Programming Language :: Python :: 3.8
Classifier: Programming Language :: Python :: 3.9
Classifier: Programming Language :: Python :: 3.10
Classifier: Programming Language :: Python :: 3.11
Classifier: Operating System :: Microsoft :: Windows
Classifier: Operating System :: Unix
Classifier: Topic :: Scientific/Engineering
Classifier: Topic :: Software Development
Requires-Python: >=3.6
License-File: LICENSE
Requires-Dist: scipy
Requires-Dist: numpy
